ImageMKS-0.1.0.data/scripts/cellanalysis
ImageMKS-0.1.0.data/scripts/imagemks
imagemks/__init__.py
imagemks/__main__.py
imagemks/clusters/__init__.py
imagemks/clusters/neighborhoods.py
imagemks/common/__init__.py
imagemks/common/size_check.py
imagemks/filters/__init__.py
imagemks/filters/_fftconvolve.py
imagemks/filters/fftedges.py
imagemks/filters/fftgaussian.py
imagemks/filters/morphological.py
imagemks/masking/__init__.py
imagemks/masking/fourier.py
imagemks/rw/__init__.py
imagemks/rw/folder.py
imagemks/structures/__init__.py
imagemks/structures/grids.py
imagemks/structures/shapes.py
imagemks/structures/weights.py
imagemks/visualization/__init__.py
imagemks/visualization/borders.py
imagemks/visualization/img_show.py
imagemks/visualization/plotting.py
imagemks/workflows/__init__.py
imagemks/workflows/fluorescentcells.py
ImageMKS-0.1.0.dist-info/LICENSE.md
ImageMKS-0.1.0.dist-info/METADATA
ImageMKS-0.1.0.dist-info/WHEEL
ImageMKS-0.1.0.dist-info/top_level.txt
ImageMKS-0.1.0.dist-info/RECORD
